DESCRIPTION.rst
MANIFEST.in
setup.cfg
setup.py
daemon/systemd/mbootstrapslad.service
daemon/systemv/mbootstrapslad
etc/marcobootstrap/scheduled.db
etc/marcobootstrap/slave/slave.cfg
etc/marcobootstrap/slave/certs/app.crt
etc/marcobootstrap/slave/certs/app.csr
etc/marcobootstrap/slave/certs/app.key
etc/marcobootstrap/slave/certs/receiver.crt
etc/marcobootstrap/slave/certs/receiver.csr
etc/marcobootstrap/slave/certs/receiver.key
marcobootstrap/__init__.py
marcobootstrap.slave.egg-info/PKG-INFO
marcobootstrap.slave.egg-info/SOURCES.txt
marcobootstrap.slave.egg-info/dependency_links.txt
marcobootstrap.slave.egg-info/entry_points.txt
marcobootstrap.slave.egg-info/namespace_packages.txt
marcobootstrap.slave.egg-info/not-zip-safe
marcobootstrap.slave.egg-info/requires.txt
marcobootstrap.slave.egg-info/top_level.txt
marcobootstrap/slave/__init__.py
marcobootstrap/slave/conf.py
marcobootstrap/slave/slave.py